setup.py
numbertoletters/__init__.py
numbertoletters.egg-info/PKG-INFO
numbertoletters.egg-info/SOURCES.txt
numbertoletters.egg-info/dependency_links.txt
numbertoletters.egg-info/not-zip-safe
numbertoletters.egg-info/top_level.txt