Metadata-Version: 1.0
Name: numbertoletters
Version: 0.1
Summary: A python library to convert a number to letters
Home-page: https://github.com/AxiaCore/number-to-letters
Author: AxiaCore
Author-email: info@axiacore.com
License: MIT
Platform: UNKNOWN
